{
  "AncientStool_Name": "Eski Tabure",
  "AncientStool_Description": "Büyükannenin evi gibi kokuyor.",
  "AncientTable_Name": "Eski Masa",
  "AncientTable_Description": "Kalın örümcek ağlarıyla kaplanmış.",
  "AutoGrabber_Name": "Otomatik Toplayıcı",
  "AutoGrabber_Description": "Her sabah hayvanlarınının ürünlerini otomatik olarak toplar. İnekler, koyunlar ve keçiler için geçerlidir.",
  "AutoPetter_Name": "Hayvan Sevici",
  "AutoPetter_Description": "Kümes ve ahırda kullanılmak üzere Joja Co.'nun geliştirdiği bir teknoloji harikası. İnsan dokunuşunun yerini tamamen almasa da hayvanları mutlu eder. Hayvanlar hala daha elle sevilebilir.",
  "Barrel_Name": "Varil",
  "Barrel_Description": "...",
  "BarrelBrazier_Name": "Varil Maltız",
  "BarrelBrazier_Description": "Orta düzeyde ışık sağlar.",
  "BasicLog_Name": "Kütük",
  "BasicLog_Description": "Çiftliğe yerleştirilebilen bir süs.",
  "BeeHouse_Name": "Arı Kovanı",
  "BeeHouse_Description": "Dışarıya yerleştir ve (kışları hariç) lezzetli balın oluşmasını bekle!",
  "BigGreenCane_Name": "Büyük Yeşil Şekerkamışı",
  "BigGreenCane_Description": "Çiftliğe yerleştirilebilen bir süs.",
  "BigRedCane_Name": "Büyük Kırmızı Şekerkamışı",
  "BigRedCane_Description": "Çiftliğe yerleştirilebilen bir süs.",
  "BoneMill_Name": "Kemik Değirmeni",
  "BoneMill_Description": "Kemikten yapılma nesneleri gübreye dönüştürür.",
  "Bonfire_Name": "Ateş",
  "Bonfire_Description": "Korlar hafiften parıldıyor.",
  "Bongo_Name": "Bongo",
  "Bongo_Description": "Zengin ses çıkaran, süs niyetine kullanılan vurmalı bir çalgı.",
  "Bookcase_Name": "Kitaplık",
  "Bookcase_Description": "Kitapların koyulduğu raflar bütünü.",
  "Boulder_Name": "Kaya",
  "Boulder_Description": "Aşırı kalın bir taş parçası.",
  "Camera_Name": "Kamera",
  "Camera_Description": "Tripoda takılı eski bir kamera.",
  "Campfire_Name": "Kamp Ateşi",
  "Campfire_Description": "Orta düzeyde ışık sağlar.",
  "Campfire_2_Name": "Kamp Ateşi",
  "Campfire_2_Description": "Evde değilken de yemek yapmayı sağlar!",
  "CarvedBrazier_Name": "Oyma Maltız",
  "CarvedBrazier_Description": "Orta düzeyde ışık sağlar.",
  "Cask_Name": "Fıçı",
  "Cask_Description": "Peynir ve şarap gibi gıdaları yıllandırmak için kilerde tutulur.",
  "CharcoalKiln_Name": "Kömür Fırını",
  "CharcoalKiln_Description": "10 parça odunu bir parça kömüre dönüştürür.",
  "CheesePress_Name": "Peynir Ezeceği",
  "CheesePress_Description": "Sütü peynire dönüştürür.",
  "Chest_Name": "Sandık",
  "Chest_Description": "Nesne koyulan bir saklama noktası.",
  "ChickenStatue_Name": "Tavuk Heykelciği",
  "ChickenStatue_Description": "Ahşaptan yapılmış tavuk heykelciği.",
  "CoffeeMaker_Name": "Kahve Makinesi",
  "CoffeeMaker_Description": "Her sabah otomatik olarak bir bardak kahve yapar.",
  "Crate_Name": "Kasa",
  "Crate_Description": "...",
  "Crystalarium_Name": "Kristalaryum",
  "Crystalarium_Description": "Çoğaltmak istediğin mücevheri koy ve bekle.",
  "CursedPKArcadeSystem_Name": "Lanetli Ç.K. Atari Oyunu",
  "CursedPKArcadeSystem_Description": "Bu Çayır Kralı atari oyununda ters bir şeyler var...",
  "DarkSign_Name": "Kara İşaret",
  "DarkSign_Description": "Görüntüleneni değiştirmek için bir nesne üzerinde kullanılır. Kullanılan nesne kaybolmaz.",
  "DeadTree_Name": "Ölü Ağaç",
  "DeadTree_Description": "Taşlaşmış, yazık.",
  "Deconstructor_Name": "Ayırıcı",
  "Deconstructor_Description": "Oluşturulan nesneleri parçalarına ayırır ve değerli materyalleri geri kazandırır.",
  "DecorativePitcher_Name": "Süslük Sürahi",
  "DecorativePitcher_Description": "El emeği verilerek pirinçten yapılmış.",
  "DecorativeSpears_Name": "Süslük Mızraklar",
  "DecorativeSpears_Description": "Güvende hissettiren süsler değil.",
  "DeluxeScarecrow_Name": "Büyük Korkuluk",
  "DeluxeScarecrow_Description": "Ekinlerini kargalardan korur. Sınırlı menzili (16 \"kare\" kadar) vardır.",
  "Door_Name": "Kapı",
  "Door_Description": "Gizli bir mekanizma, kapıyı gerisin geriye yere çeker.",
  "DriedSunflowers_Name": "Kurumuş Ayçicekleri",
  "DriedSunflowers_Description": "Canlı süslerden.",
  "EmptyCapsule_Name": "Boş Kapsül",
  "EmptyCapsule_Description": "Cam parçalanmış.",
  "FancyTable_Name": "Süslü Masa",
  "FancyTable_Description": "Güzelcene yapılmış bir masa.",
  "FarmComputer_Name": "Çiftlik Bilgisayarı",
  "FarmComputer_Description": "Çiftliği tarar ve önemli bilgiler sunar.",
  "FeedHopper_Name": "Yem Hunisi",
  "FeedHopper_Description": "Silodaki yeme doğrudan erişim sağlar.",
  "Foroguemon_Name": "??Forokemon??",
  "Foroguemon_Description": "??Forokemon??",
  "Furnace_Name": "Ocak",
  "Furnace_Description": "Cevher ve kömürü metalik külçelere dönüştürür.",
  "GardenPot_Name": "Saksı",
  "GardenPot_Description": "İçerdeyken her mevsimden bitkiyi, dışardayken sadece mevsimsel bitkileri yetiştirebilir.",
  "GeodeCrusher_Name": "Jeotkırar",
  "GeodeCrusher_Description": "Jeotları otomatik olarak kırar.",
  "GoldBrazier_Name": "Altın Maltız",
  "GoldBrazier_Description": "Orta düzeyde ışık sağlar.",
  "GrandfatherClock_Name": "Büyükbaba Saati",
  "GrandfatherClock_Description": "Aşırı eski... görünüşe göre sarkaç pasla sabitlenmiş.",
  "GraveStone_Name": "Mezar Taşı",
  "GraveStone_Description": "Çiftliğe yerleştirilebilen bir süs.",
  "GreenCanes_Name": "Yeşil Şekerkamışları",
  "GreenCanes_Description": "Çiftliğe yerleştirilebilen bir süs.",
  "Heater_Name": "Isıtıcı",
  "Heater_Description": "Hayvanlarını kışın mutlu ve sıcak tutar.",
  "HeavyTapper_Name": "Büyük Akıtaç",
  "HeavyTapper_Description": "Meşe, akçaağaç ya da çam ağacına takılır. Sonrasında ise ağaçların verdiği ürünlerle dolması beklenir. Sıradan bir akıtaçın iki katı hızla çalışır!",
  "HMTGF_Name": "??HMTGF??",
  "HMTGF_Description": "??HMTGF??",
  "Hopper_Name": "Huni",
  "Hopper_Description": "İçine konulan nesneleri doğrudan önündeki makineye aktarır.",
  "HousePlant_Name": "Ev Bitkisi",
  "HousePlant_Description": "Evine ya da çiftliğine biraz renk getirir.",
  "Incubator_Name": "Kuluçka Makinesi",
  "Incubator_Description": "Yumurtalardan civciv çıkmasını sağlar.",
  "IronLamppost_Name": "Demir Lamba Direği",
  "IronLamppost_Description": "Orta düzeyde ışık sağlar.",
  "ItemPedestal_Name": "Item Pedestal",
  "ItemPedestal_Description": "A place to display an item.",
  "JunimoChest_Name": "Junimo Sandığı",
  "JunimoChest_Description": "Orman büyüsünün gücünü kullanan her bir Junimo sandığı aynı zulaya bağlıdır.",
  "JunimoKartArcadeSystem_Name": "Junimo Kart Atari Oyunu",
  "JunimoKartArcadeSystem_Description": "'Junimo Kart' oyununu evden oynamayı sağlar!",
  "Keg_Name": "Fıçı",
  "Keg_Description": "Meyve ya da sebze yerleştir. Eninde sonunda bir içeceğe dönüşecektir.",
  "LawnFlamingo_Name": "Flamingo",
  "LawnFlamingo_Description": "Çiftliğe yerleştirilebilen bir süs.",
  "LightningRod_Name": "Paratoner",
  "LightningRod_Description": "Düşen yıldırımdan enerji toplar ve bu enerjiyle pil oluşmasını sağlar.",
  "LockedDoor_Name": "Kilitli Kapı",
  "LockedDoor_Description": "Gizli bir mekanizma, kapıyı gerisin geriye yere çeker.",
  "LogSection_Name": "Ağaç Gövdesi",
  "LogSection_Description": "Çiftliğe yerleştirilebilen bir süs.",
  "Loom_Name": "Dokuma Tezgahı",
  "Loom_Description": "Yünü kaliteli kumaşa dönüştürür.",
  "MarbleBrazier_Name": "Mermer Maltız",
  "MarbleBrazier_Description": "Orta düzeyde ışık sağlar.",
  "MayonnaiseMachine_Name": "Mayonez Makinesi",
  "MayonnaiseMachine_Description": "Yumurtadan mayonez üretir.",
  "MiniFridge_Name": "Küçük Buzdolabı",
  "MiniFridge_Description": "Fazla gelen yemek malzemelerini saklamaya yarar.",
  "MiniJukebox_Name": "Küçük Müzik Kutusu",
  "MiniJukebox_Description": "En sevdiğin parçaları çalmaya yarar.",
  "MiniObelisk_Name": "Küçük Dikilitaş",
  "MiniObelisk_Description": "Çiftlikteki iki nokta arasında ışınlanmayı sağlar.",
  "MiniShippingBin_Name": "Küçük Gönderi Kutusu",
  "MiniShippingBin_Description": "Geceleri satılmasını istediğin malları kutuya koy.",
  "MixedCane_Name": "Renkli Şekerkamışları",
  "MixedCane_Description": "Çiftliğe yerleştirilebilen bir süs.",
  "MushroomBox_Name": "Mantar Kutusu",
  "MushroomBox_Description": "Birkaç gün aralıklarla mantar yetişir.",
  "Obelisk_Name": "Dikilitaş",
  "Obelisk_Description": "Kötü enerji yayan, uğursuz görünen bir portal.",
  "ObsidianVase_Name": "Obsidyen Vazo",
  "ObsidianVase_Description": "Obsidyen ve altından yapılmış, harika işçiliğe sahip olan süs vazosu.",
  "OilMaker_Name": "Yağ Üreteci",
  "OilMaker_Description": "Yermantarı yağı üretir.",
  "OrnamentalHayBale_Name": "Süslük Saman Balyası",
  "OrnamentalHayBale_Description": "Çiftliğe yerleştirilebilen bir süs.",
  "OstrichIncubator_Name": "Devekuşu Kuluçka Makinesi",
  "OstrichIncubator_Description": "Yumurtalardan devekuşu çıkmasını sağlar. Ahıra yerleştirilir.",
  "PinkyLemon_Name": "??Pembemsi Limon??",
  "PinkyLemon_Description": "??Pembemsi Limon??",
  "PlushBunny_Name": "Peluş Tavşan",
  "PlushBunny_Description": "Büyük, yumuşak ve tatlı.",
  "PrairieKingArcadeSystem_Name": "Çayır Kralı Atari Oyunu",
  "PrairieKingArcadeSystem_Description": "'Çayır Kralı'nın Yolculuğu'nu evden oynamayı sağlar!",
  "PreservesJar_Name": "Kavanoz",
  "PreservesJar_Description": "Sebzeleri turşuya, meyveleri ise reçele dönüştürür.",
  "RareCrow_1_Name": "İlginç Korkuluk",
  "RareCrow_1_Description": "Hepsini bul! (1",
  "RareCrow_2_Name": "İlginç Korkuluk",
  "RareCrow_2_Description": "Hepsini bul! (2",
  "RareCrow_3_Name": "İlginç Korkuluk",
  "RareCrow_3_Description": "Hepsini bul! (3",
  "RareCrow_4_Name": "İlginç Korkuluk",
  "RareCrow_4_Description": "Hepsini bul! (4",
  "RareCrow_5_Name": "İlginç Korkuluk",
  "RareCrow_5_Description": "Hepsini bul! (5",
  "RareCrow_6_Name": "İlginç Korkuluk",
  "RareCrow_6_Description": "Hepsini bul! (6",
  "RareCrow_7_Name": "İlginç Korkuluk",
  "RareCrow_7_Description": "Hepsini bul! (7",
  "RareCrow_8_Name": "İlginç Korkuluk",
  "RareCrow_8_Description": "Hepsini bul! (8",
  "RecyclingMachine_Name": "Geri Dönüşüm Makinesi",
  "RecyclingMachine_Description": "Balık tutarken bulunan çöpleri kullanışlı nesnelere dönüştürür.",
  "RedCanes_Name": "Kırmızı Şekerkamışları",
  "RedCanes_Description": "Çiftliğe yerleştirilebilen bir süs.",
  "RitualMask_Name": "Tören Maskesi",
  "RitualMask_Description": "Takmak için fazlasıyla büyük.",
  "Scarecrow_Name": "Korkuluk",
  "Scarecrow_Description": "Ekinlerini kargalardan korur. Sınırlı menzili (8 \"kare\" kadar) vardır.",
  "SeasonalDecor_Name": "Mevsim Süsü",
  "SeasonalDecor_Description": "Bu süs mevsimle birlikte değişir.",
  "SeasonalPlant_Name": "Mevsimsel Bitki",
  "SeasonalPlant_Description": "Mevsimden mevsime değişen bir süs bitkisi. Sulanması gerekmez.",
  "SeedMaker_Name": "Tohum Üreteci",
  "SeedMaker_Description": "Değişik miktarda tohum elde etmek için içine ekin yerleştirilir. Ağaçların verdiği meyvelerle çalışmaz.",
  "SewingMachine_Name": "Dikiş Makinesi",
  "SewingMachine_Description": "Evde giysi dikmeye yarar!",
  "SignOfTheVessel_Name": "İşaret Heykeli",
  "SignOfTheVessel_Description": "Çiftliğe yerleştirilebilen bir süs.",
  "SingingStone_Name": "Şarkıcı Taş",
  "SingingStone_Description": "Vurulduğunda notaları en düzgün halleriyle çıkartır.",
  "SkeletonModel_Name": "İskelet",
  "SkeletonModel_Description": "Bir iskelet maketi.",
  "SkullBrazier_Name": "Kemik Maltız",
  "SkullBrazier_Description": "Orta düzeyde ışık sağlar.",
  "SlimeBall_Name": "Balçıkça Topu",
  "SlimeBall_Description": "Balçıkça dolu.",
  "SlimeEggPress_Name": "Balçıkça Yumurta Üreteci",
  "SlimeEggPress_Description": "100 adet balçıkçayı sıkıştırarak balçıkça yumurtası oluşturur. Bilimsel bir mucize gerçekleştirir!",
  "SlimeIncubator_Name": "Balçıkça Kuluçka Makinesi",
  "SlimeIncubator_Description": "Balçıkça yumurtalarını kulukçaya alır. Evin dışında balçıkça yetiştirmeyi mümkün kılar.",
  "SlothSkeletonL_Name": "Tembel Hayvan İskeleti",
  "SlothSkeletonL_Description": "Nesli tükenmiş bu tembel hayvan, bilinen tarihin öncesinde kalan zamanlarda Yıldızçiyi Vadisi'nin bereketli topraklarında dolaşmış. Güçlü çenesiyle en sert bitki liflerini bile parçalarmış.",
  "SlothSkeletonM_Name": "Tembel Hayvan İskeleti",
  "SlothSkeletonM_Description": "Tarih öncesine ait bir tembel hayvan kaburgası.",
  "SlothSkeletonR_Name": "Tembel Hayvan İskeleti",
  "SlothSkeletonR_Description": "Tarih öncesine ait bir tembel hayvanın arka ayakları ve kuyruğu.",
  "SodaMachine_Name": "Otomat",
  "SodaMachine_Description": "Durmaksızın güzel ürünler verir.",
  "SolarPanel_Name": "Güneş Paneli",
  "SolarPanel_Description": "Güneş ışığı vurduğunda yavaşça pil üretir.",
  "SolidGoldLewis_Name": "Altın Lewis",
  "SolidGoldLewis_Description": "Başkanın gizli projesi.",
  "Staircase_Name": "Merdiven",
  "Staircase_Description": "Madende bir seviye aşağıya inmede kullanılır.",
  "StandingGeode_Name": "Dikili Jeot",
  "StandingGeode_Description": "Dikili duran koca bir jeot. İçinde bulunan yüzlerce mor kristalin parıltısı görülüyor.",
  "StardewHeroTrophy_Name": "Yıldızçiyi Kahramanı Ödülü",
  "StardewHeroTrophy_Description": "Bir Yıldızçiyi Vadisi sakininin alabileceği en prestijli ödül!",
  "StatueOfEndlessFortune_Name": "Sonsuz Talih Heykelciği",
  "StatueOfEndlessFortune_Description": "Som altından yapılmış. Ne işe yarar ki?",
  "StatueOfPerfection_Name": "Mükemmellik Heykeli",
  "StatueOfPerfection_Description": "Saf iridyumdan yapılmıştır.",
  "StatueOfTruePerfection_Name": "Gerçek Mükemmellik Heykeli",
  "StatueOfTruePerfection_Description": "Saf iridyumdan yapılmıştır.",
  "StoneBrazier_Name": "Taş Maltız",
  "StoneBrazier_Description": "Orta düzeyde ışık sağlar.",
  "StoneCairn_Name": "Taş Yığını",
  "StoneCairn_Description": "Çiftliğe yerleştirilebilen bir süs.",
  "StoneChest_Name": "Taş Sandık",
  "StoneChest_Description": "Nesne koyulan bir saklama noktası.",
  "StoneFrog_Name": "Taş Kurbağa",
  "StoneFrog_Description": "Bahçeye yerleştirilebilen sanat eseri.",
  "StoneJunimo_Name": "Taş Junimo",
  "StoneJunimo_Description": "Bahçeye yerleştirilebilen sanat eseri.",
  "StoneOwl_Decorative_Name": "Taş Baykuş",
  "StoneOwl_Decorative_Description": "Bahçeye yerleştirilebilen sanat eseri.",
  "StoneOwl_Secret_Name": "Taş Baykuş",
  "StoneOwl_Secret_Description": "Nereden geldiği belli olmasa da harika görünüyor.",
  "StoneParrot_Name": "Taş Papağan",
  "StoneParrot_Description": "Bahçeye yerleştirilebilen sanat eseri.",
  "StoneSign_Name": "Taş Tabela",
  "StoneSign_Description": "Yazıyı değiştirmek için üstünde eşya kullanılır. Eşya harcanmaz.",
  "StrangeCapsule_Name": "Garip Kapsül",
  "StrangeCapsule_Description": "Sıvının içinde büyük bir şey var...",
  "StumpBrazier_Name": "Kütük Maltız",
  "StumpBrazier_Description": "Orta düzeyde ışık sağlar.",
  "SuitOfArmor_Name": "Zırh",
  "SuitOfArmor_Description": "Çiftliğe yerleştirilebilen bir süs.",
  "TablePieceL_Name": "Sl. Masa Parçası",
  "TablePieceL_Description": "Büyük bir masanın sol tarafı.",
  "TablePieceR_Name": "Sğ. Masa Parçası",
  "TablePieceR_Description": "Büyük bir masanın sağ tarafı.",
  "TallTorch_Name": "Uzun Meşale",
  "TallTorch_Description": "Sapı bambudan yapılmış.",
  "Tapper_Name": "Akıtaç",
  "Tapper_Description": "Meşe, akçaağaç ya da çam ağacına takılır. Sonrasında ise ağaçların verdiği ürünlerle dolması beklenir!",
  "TeddyTimer_Name": "Ayıcık Saati",
  "TeddyTimer_Description": "Büyükbaba saati gibi ama ayıcık şeklinde.",
  "Telephone_Name": "Telefon",
  "Telephone_Description": "Mevcut ürünleri ve açılış kapanış saatlerini öğrenmede kullanılır.",
  "TuboFlowers_Name": "Çiçek Küveti",
  "TuboFlowers_Description": "Meşeden yapılma küvete konulmuş çiçekler. Yaz ve bahar mevsimlerinde açarlar.",
  "WickedStatue_Name": "Uğursuz Heykel",
  "WickedStatue_Description": "Bu heykelin görüntüsünde insanı rahatsız eden bir şey var.",
  "WickedStatue_LitEyes_Name": "Uğursuz Heykel",
  "WickedStatue_LitEyes_Description": "Bu heykelde yanlış olan bir şey var.",
  "WoodChair_Name": "Ahşap Sandalye",
  "WoodChair_Description": "Bakış yönü değiştirilebilen sandalye.",
  "WoodChipper_Name": "Ağaç Öğütücü",
  "WoodChipper_Description": "Yerleştirilen keresteyi böler ve oduna dönüştürür.",
  "WoodenBrazier_Name": "Ahşap Maltız",
  "WoodenBrazier_Description": "Orta düzeyde ışık sağlar.",
  "WoodLamppost_Name": "Ahşap Lamba Direği",
  "WoodLamppost_Description": "Orta düzeyde ışık sağlar.",
  "WoodSign_Name": "Ahşap Tabela",
  "WoodSign_Description": "Yazıyı değiştirmek için üstünde eşya kullanılır. Eşya harcanmaz.",
  "Workbench_Name": "Çalışma Tezgahı",
  "Workbench_Description": "Nesne oluştururken bitişiğindeki sandıklardaki malzemelere erişim sağlar.",
  "WormBin_Name": "Solucan Kutusu",
  "WormBin_Description": "Düzenli olarak yem üretir. Solucanlar kendi başlarına idare eder.",
  "TextSign_Name": "Tabela",
  "TextSign_Description": "Üzerine yazı yazılabilen küçük bir tabela.",
  "MushroomLog_Name": "Mantar Kütüğü",
  "MushroomLog_Description": "Sıklıkla mantar yetiştirir. Etrafında ne kadar ağaç varsa o kadar etkili olur.",
  "BaitMaker_Name": "Yem Yapıcı",
  "BaitMaker_Description": "Seçili bir yemi üretmek için içine balık koy.",
  "Dehydrator_Name": "Dehidratör",
  "Dehydrator_Description": "Kurutmak için içine 5 parça meyve veya yenebilir mantar koy.",
  "HeavyFurnace_Name": "Ağır Ocak",
  "HeavyFurnace_Description": "Tek seferde 5 külçe oluşturur. Her kullanım için 25 parça cevher ve 3 kömür gerekir.",
  "StatueOfBlessings_Name": "Lütufların Heykeli",
  "StatueOfBlessings_Description": "Bu heykele dokunmak, her gün özel bir lütuf verir.",
  "StatueOfTheDwarfKing_Name": "Cüce Kralın Heykeli",
  "StatueOfTheDwarfKing_Description": "Her gün iki madencilikle alakalı güçlendirmeden birini seç.",
  "Anvil_Name": "Örs",
  "Anvil_Description": "Aksesuarları \"yeniden oluşturmana\" yarar. Her kullanım için 3 iridyum külçesi gerekir.",
  "MiniForge_Name": "Mini Dökümhane",
  "MiniForge_Description": "Artık cüce dökümhanesini evinin rahatlığında kullanabilirsin."
}