{
  "DarkPiano": "Piano oscuro",
  "OakChair": "Silla de roble",
  "WalnutChair": "Silla de nogal",
  "BirchChair": "Silla de abedul",
  "MahoganyChair": "Silla de caoba",
  "RedDinerChair": "Silla roja",
  "BlueDinerChair": "Silla azul",
  "CountryChair": "Silla rústica",
  "BreakfastChair": "Silla de desayuno",
  "PinkOfficeChair": "Silla de oficina rosa",
  "PurpleOfficeChair": "Silla de oficina lila",
  "GreenOfficeStool": "Taburete de oficina verde",
  "OrangeOfficeStool": "Taburete de oficina naranja",
  "DarkThrone": "Trono oscuro",
  "DiningChair": "Silla de comedor",
  "GreenPlushSeat": "Asiento afelpado verde",
  "PinkPlushSeat": "Asiento afelpado rosa",
  "WinterChair": "Silla de invierno",
  "GroovyChair": "Silla elegante",
  "CuteChair": "Silla mona",
  "StumpSeat": "Asiento de tocón",
  "MetalChair": "Silla de metal",
  "GreenStool": "Taburete verde",
  "BlueStool": "Taburete azul",
  "KingChair": "Silla real",
  "CrystalChair": "Silla de cristal",
  "OakBench": "Banco de roble",
  "WalnutBench": "Banco de nogal",
  "BirchBench": "Banco de abedul",
  "MahoganyBench": "Banco de caoba",
  "ModernBench": "Banco moderno",
  "BlueArmchair": "Sillón azul",
  "RedArmchair": "Sillón rojo",
  "GreenArmchair": "Sillón verde",
  "YellowArmchair": "Sillón amarillo",
  "BrownArmchair": "Sillón marrón",
  "BlueCouch": "Sofá azul",
  "RedCouch": "Sofá rojo",
  "GreenCouch": "Sofá verde",
  "YellowCouch": "Sofá amarillo",
  "BrownCouch": "Sofá marrón",
  "DarkCouch": "Sofá oscuro",
  "WizardCouch": "Sofá de mago",
  "WoodsyCouch": "Sofá silvestre",
  "OakDresser": "Cómoda de roble",
  "WalnutDresser": "Cómoda de nogal",
  "BirchDresser": "Cómoda de abedul",
  "MahoganyDresser": "Cómoda de caoba",
  "CoffeeTable": "Mesa de centro",
  "StoneSlab": "Losa de piedra",
  "WinterDiningTable": "Mesa de comedor de invierno",
  "FestiveDiningTable": "Mesa de comedor festiva",
  "MahoganyDiningTable": "Mesa de comedor de caoba",
  "ModernDiningTable": "Mesa de comedor moderna",
  "OakTable": "Mesa de roble",
  "WalnutTable": "Mesa de nogal",
  "BirchTable": "Mesa de abedul",
  "MahoganyTable": "Mesa de caoba",
  "SunTable": "Mesa sol",
  "MoonTable": "Mesa luna",
  "ModernTable": "Mesa moderna",
  "PubTable": "Mesa de pub",
  "LuxuryTable": "Mesa de lujo",
  "DivinerTable": "Mesa de adivinación",
  "NeolithicTable": "Mesa neolítica",
  "PuzzleTable": "Mesa puzzle",
  "WinterTable": "Mesa de invierno",
  "CandyTable": "Mesa de caramelo",
  "LuauTable": "Mesa de luau",
  "DarkTable": "Mesa oscura",
  "OakTeaTable": "Mesa de té de roble",
  "WalnutTeaTable": "Mesa de té de nogal",
  "BirchTeaTable": "Mesa de té de abedul",
  "MahoganyTeaTable": "Mesa de té de caoba",
  "ModernTeaTable": "Mesa de té moderna",
  "FurnitureCatalogue": "Catálogo de muebles",
  "ChinaCabinet": "Vitrina para porcelana",
  "ArtistBookcase": "Estantería artística",
  "LuxuryBookcase": "Estantería de lujo",
  "ModernBookcase": "Estantería moderna",
  "DarkBookcase": "Estantería oscura",
  "CeramicPillar": "Pilar de cerámica",
  "GoldPillar": "Pilar de oro",
  "IndustrialPipe": "Tubería industrial",
  "IndoorPalm": "Palmera de interior",
  "TotemPole": "Tótem",
  "ManicuredPine": "Pino bien cuidado",
  "TopiaryTree": "Árbol podado",
  "StandingGeode": "Geoda vertical",
  "ObsidianVase": "Jarrón de obsidiana",
  "SingingStone": "Piedra musical",
  "SlothSkeletonL": "Esqueleto de perezoso A",
  "SlothSkeletonM": "Esqueleto de perezoso B",
  "SlothSkeletonR": "Esqueleto de perezoso C",
  "Skeleton": "Esqueleto",
  "ChickenStatue": "Estatua de gallina",
  "LeahsSculpture": "Escultura de Leah",
  "DriedSunflowers": "Girasoles secos",
  "Catalogue": "Catálogo",
  "SamsBoombox": "Radio de Sam",
  "SmallPlant": "Planta pequeña",
  "TablePlant": "Planta de mesa",
  "DecorativeBowl": "Bol decorativo",
  "FutanBear": "Oso de peluche",
  "Globe": "Globo",
  "ModelShip": "Maqueta de barco",
  "SmallCrystal": "Minicristal",
  "DecorativeLantern": "Faro decorativo",
  "HousePlant": "Planta de interior",
  "OakEndTable": "Mesilla de roble",
  "WalnutEndTable": "Mesilla de nogal",
  "BirchEndTable": "Mesilla de abedul",
  "MahoganyEndTable": "Mesilla de caoba",
  "ModernEndTable": "Mesilla moderna",
  "GrandmotherEndTable": "Mesilla de abuelita",
  "WinterEndTable": "Mesilla de invierno",
  "Calendar": "Calendario",
  "TreeoftheWinterStar": "Árbol de la estrella invernal",
  "CountryLamp": "Lámpara rústica",
  "BoxLamp": "Lámpara cuadrada",
  "ModernLamp": "Lámpara moderna",
  "ClassicLamp": "Lámpara clásica",
  "RedRug": "Alfombra roja",
  "PatchworkRug": "Alfombra de retales",
  "DarkRug": "Alfombra oscura",
  "BudgetTV": "Televisor barato",
  "PlasmaTV": "Televisor de plasma",
  "TheMuzzamaroo": "«El Muzzamaroo»",
  "ANightOnEcoHill": "«Una noche en Eco-Hill»",
  "Pathways": "«Caminos»",
  "BurntOffering": "«Ofrenda quemada»",
  "QueenoftheGemSea": "«Reina del mar de Gema»",
  "VanillaVilla": "«Villa Vainilla»",
  "PrimalMotion": "«Movimiento primario»",
  "JadeHills": "«Colinas de jade»",
  "Sun44": "«Sol #44»",
  "WallflowerPal": "Personaje simpático",
  "Spires": "«Torreones»",
  "Highway89": "«Autopista 89»",
  "CalicoFalls": "«Cataratas Calico»",
  "NeedlepointFlower": "Flor de punto de cruz",
  "SkullPoster": "Póster de calavera",
  "Sun45": "«Sol #45»",
  "LittleTree": "«Arbolito»",
  "Blueberries": "«Arándanos»",
  "BlueCity": "«Ciudad azul»",
  "LittlePhotos": "Fotos pequeñas",
  "DancingGrass": "«Hierba danzante»",
  "VGAParadise": "«Paraíso VGA»",
  "JColaLight": "Neón Joja-Cola",
  "Kitemaster95": "«As de la cometa del 95»",
  "BasicWindow": "Ventana básica",
  "SmallWindow": "Ventana pequeña",
  "RedCottageRug": "Alfombra de cabaña roja",
  "GreenCottageRug": "Alfombra de cabaña verde",
  "MonsterRug": "Alfombra monstruosa",
  "BoardedWindow": "Ventana tapiada",
  "MysticRug": "Alfombra mística",
  "LgFutanBear": "Oso de peluche XL",
  "JunimoPlush": "Junimo de peluche",
  "BearStatue": "Estatua de oso",
  "Porthole": "Ojo de buey",
  "Anchor": "Ancla",
  "WorldMap": "Mapamundi",
  "OrnateWindow": "Ventana ornamental",
  "FloorTV": "Televisor de suelo",
  "CarvedWindow": "Ventana oriental",
  "NauticalRug": "Alfombra náutica",
  "BurlapRug": "Alfombra de mimbre",
  "TreeColumn": "Columna silvestre",
  "LLightString": "Muérdago",
  "SPine": "Minipino",
  "BonsaiTree": "Bonsái",
  "MetalWindow": "Ventana metálica",
  "CandleLamp": "Candil",
  "MinersCrest": "Adorno minero",
  "BambooMat": "Esterilla de bambú",
  "OrnateLamp": "Lámpara ornamental",
  "WoodcutRug": "Alfombra de madera",
  "HangingShield": "Escudo de pared",
  "MonsterDanglers": "Pegatinas monstruosas",
  "CeilingFlags": "Banderines",
  "RedEagle": "\"Águila roja\"",
  "PortraitOfAMermaid": "\"Retrato de una sirena\"",
  "SolarKingdom": "\"Reino solar\"",
  "Clouds": "\"Nubes\"",
  "1000YearsFromNow": "\"Dentro de 1000 años\"",
  "ThreeTrees": "\"Tres árboles\"",
  "TheSerpent": "\"La serpiente\"",
  "TropicalFish173": "\"Pez tropical número 173\"",
  "LandOfClay": "\"Tierra de arcilla\"",
  "BrickFireplace": "Chimenea de ladrillo",
  "StoneFireplace": "Chimenea de piedra",
  "IridiumFireplace": "Chimenea de iridio",
  "StoveFireplace": "Chimenea de fogón",
  "MonsterFireplace": "Chimenea monstruosa",
  "MyFirstPainting": "Mi primer cuadro",
  "ElegantFireplace": "Chimenea elegante",
  "PirateFlag": "Bandera pirata",
  "PirateRug": "Alfombra pirata",
  "BoneRug": "Alfombra huesuda",
  "ButterflyHutch": "Nido de Mariposas",
  "StrawberryDecal": "Calcomanía de fresa",
  "FruitSaladRug": "Alfombra de ensalada de frutas",
  "NightSkyDecal1": "Calcomanía cielo nocturno nº1",
  "SnowyRug": "Alfombra nevada",
  "NightSkyDecal2": "Calcomanía cielo nocturo nº2",
  "NightSkyDecal3": "Calcomanía cielo nocturno nº3",
  "TheBraveLittleSapling": "«El valiente pequeño arbolito»",
  "Mysterium": "«Misterium»",
  "JourneyOfThePrairieKingTheMotionPicture": "«Viaje del Rey de la Pradera: la película»",
  "Wumbus": "«Wumbus»",
  "TheZuzuCityExpress": "«El expreso a Ciudad Zuzu»",
  "TheMiracleAtColdstarRanch": "«Milagro en rancho Estrellafría»",
  "NaturalWondersExploringOurVibrantWorld": "«Maravillas naturales: explorando nuestro exhuberante mundo»",
  "ItHowlsInTheRain": "«Aúlla bajo la lluvia»",
  "IndoorHangingBasket": "Canasta de interior",
  "WinterTreeDecal": "Calcomanía árbol de invierno",
  "SmallJunimoPlush": "Peluche junimo pequeño",
  "FutanRabbit": "Conejo Futan",
  "WumbusStatue": "Escultura de Wumbus",
  "BoboStatue": "Escultura de Bobo",
  "PurpleSerpentStatue": "Escultura de serpiente morada",
  "GreenSerpentStatue": "Escultura de serpiente verde",
  "LongPalm": "Palmera larga",
  "LongCactus": "Cactus largo",
  "ExoticTree": "Árbol exótico",
  "DeluxeTree": "Árbol de lujo",
  "WallPumpkin": "Calabaza de pared",
  "SmallWallPumpkin": "Calabaza pequeña de pared",
  "Bed": "Cama",
  "DoubleBed": "Cama doble",
  "StarryDoubleBed": "Cama doble estrellada",
  "StrawberryDoubleBed": "Cama doble de frambuesa",
  "PirateDoubleBed": "Cama doble de pirata",
  "ChildBed": "Cama de niño",
  "TropicalBed": "Cama tropical",
  "TropicalDoubleBed": "Cama doble tropical",
  "DeluxeRedDoubleBed": "Cama doble roja de lujo",
  "ModernDoubleBed": "Cama doble moderna",
  "LargeFishTank": "Pecera grande",
  "DeluxeFishTank": "Pecera de lujo",
  "SmallFishTank": "Pecera pequeña",
  "OceanicRug": "Alfombra oceánica",
  "TropicalTV": "Televisión tropical",
  "VolcanoPhoto": "Foto de un volcán",
  "JungleTorch": "Antorcha de la jungla",
  "PalmWallOrnament": "Palmera de pared",
  "TropicalChair": "Silla tropical",
  "AquaticSanctuary": "Santuario acuático",
  "ModernFishTank": "Pecera mdoerna",
  "WildDoubleBed": "Cama doble salvaje",
  "FisherDoubleBed": "Cama doble del pescador",
  "BirchDoubleBed": "Cama doble de abedul",
  "ExoticDoubleBed": "Cama doble exótica",
  "Lifesaver": "Salvavidas",
  "FoliagePrint": "Cuadro de vegetación",
  "Boat": "«Barco»",
  "Vista": "«Paisaje»",
  "WallBasket": "Maceta de pared",
  "DecorativeTrashCan": "Papelera decorativa",
  "IridiumKrobus": "Krobus de iridio",
  "GourmandStatue": "Estatua del Goloso",
  "PyramidDecal": "Pegatina pirámide",
  "PlainTorch": "Antorcha simple",
  "StumpTorch": "Antorcha de tocón",
  "WallFlower": "Pegatina de flor",
  "SWallFlower": "Pegatina de flor (Pequeña)",
  "CloudsBanner": "Bandera de nube",
  "ColorfulSet": "Pinturas Coloridas",
  "PastelBanner": "Bandera de color pastel",
  "WinterBanner": "Bandera de invierno",
  "MoonlightJelliesBanner": "Bandera de medusa lunar",
  "JungleDecal": "Pegatina de la selva",
  "StarportDecal": "Pegatina de puerto estelar",
  "DecorativePitchfork": "Horquilla decorativa",
  "WoodPanel": "Panel de madera",
  "DecorativeAxe": "Hacha decorativa",
  "LogPanel": "Panel de tronco",
  "CeilingLeaves": "Pegatinas de hojas",
  "CloudDecal": "Calcomanía de nube",
  "FloorDividerR": "Divisor de piso D",
  "FloorDividerL": "Divisor de piso I",
  "LightGreenRug": "Alfombra verde claro",
  "JadeHillsExtended": "«Colinas de jade: grande»",
  "LargeBrownCouch": "Gran sofá marrón",
  "LargeGreenRug": "Gran alfombra verde",
  "IcyRug": "Alfombra de hielo",
  "OldWorldRug": "Alfombra rústica",
  "LargeRedRug": "Alfombra roja grande",
  "FrozenDreams": "«Sueños congelados»",
  "IcyBanner": "Bandera de hielo",
  "WallPalm": "Pegatina Palmera",
  "WallCactus": "Pegatina cactus",
  "LargeCottageRug": "Alfombra de cabaña grande",
  "Physics101": "«Física 101»",
  "WallSconce": "Aplique de la pared",
  "BlossomRug": "Alfombra de flores",
  "FunkyRug": "Alfombra Funky",
  "ModernRug": "Alfombra moderna",
  "SquirrelFigurine": "Figurilla de ardilla",
  "Cactus": "Cactus",
  "HangingFish": "Pez colgante",
  "RetroTV": "Televisión retro",
  "ArtPhoto": "Foto artística",
  "ArtPhoto2": "Foto artística 2",
  "ShortBookcase": "Librería baja",
  "PierresSign": "Letrero de Pierre",
  "SamsSkateboard": "Monopatín de Sam",
  "ChickenDecal": "Calcomanía de gallina",
  "ExoticPalace": "Palacio exótico",
  "PeriodicTable": "Tabla periódica",
  "DustySkull": "Cráneo polvoriento",
  "RadioDesk": "Mesa de radio",
  "ModelPlanes": "Maquetas de avión",
  "CalicoStatue": "Estatua Calicó",
  "SunDunes": "Dunas solares",
  "DesertTable": "Mesa del desierto",
  "DesertChair": "Silla del desierto",
  "DesertFireplace": "Chimenea del desierto",
  "SandyRug": "Alfombra arenosa",
  "DesertRug": "Alfombra del desierto",
  "DesertEndTable": "Mesilla del desierto",
  "DesertFlags": "Banderas del desierto",
  "DecorativeBarrel": "Barril decorativo",
  "MountedTrout": "Trucha de pared",
  "SquidKid": "« Niño calamar »",
  "CowDecal": "Calcomanía de vaca",
  "BluePinstripeBed": "Cama a rayas azul",
  "JungleTank": "Tanque de jungla",
  "CCFishTank": "CC Tanque de Peces",
  "BluePinstripeDoubleBed": "Cama doble a rayas azul",
  "JojaBed": "Cama Joja",
  "JojaVault": "Caja fuerte Joja",
  "JojaChair": "Silla Joja",
  "J": "J",
  "JojaColaTeaTable": "Mesita de té Joja Cola",
  "JojaTable": "Mesa Joja",
  "JPainting": "J. cuadro",
  "JLight": "J. luz",
  "JojaCatalogue": "Catálogo de muebles Joja",
  "JojaColaPainting": "Cuadro Joja Cola",
  "JojaColaOrnament": "Ornamento Joja Cola",
  "JojaFireplace": "Chimenea Joja",
  "JojaColaCans": "Latas de Joja Cola",
  "CashRegister": "Caja registradora",
  "PlasticPlant": "Planta de plástico",
  "PlasticSapling": "Arbolito de plástico",
  "GrayJojaCushion": "Cojín Joja gris",
  "JojaCushion": "Cojín Joja",
  "StackedJojaBoxes": "Cajas apiladas Joja",
  "JojaCouch": "Sofá Joja",
  "MorrisPortrait": "Gerente del año",
  "JojaHQPainting": "Cuadro Joja HD",
  "JojaCrate": "Caja Joja",
  "JojaShoppingCart": "Carrito de compra Joja",
  "LargeJojaCrate": "Caja grande Joja",
  "JojaColaFridge": "Nevera Joja Cola",
  "JojaDresser": "Cómoda Joja",
  "GrayJojaDresser": "Cómoda Joja gris",
  "LargeJojaRug": "Alfombra grande Joja",
  "SmallJojaRug": "Alfombra pequeña Joja",
  "SquareJojaRug": "Alfombra cuadrada Joja",
  "JojaRug": "Alfombra Joja",
  "JojaCoffeeTable": "Mesa de centro Joja",
  "GrayJojaCoffeeTable": "Mesa de centro Joja gris",
  "JojaLamp": "Lámpara Joja",
  "GrayJojaBookcase": "Librería Joja gris",
  "JojaBookcase": "Librería Joja",
  "JojaStool": "Taburete Joja",
  "JojaEndTable": "Mesilla Joja",
  "GrayJojaEndTable": "Mesilla Joja gris",
  "DecorativeJojaDoor": "Puerta decorativa Joja",
  "WizardBed": "Cama de mago",
  "LargeWizardBookcase": "Librería de mago grande",
  "WizardBookcase": "Librería de mago",
  "ShortWizardBookcase": "Librería de mago baja",
  "SmallWizardBookcase": "Librería de mago pequeña",
  "WizardStool": "Taburete de mago",
  "WizardFireplace": "Chimenea de mago",
  "WizardDresser": "Cómoda de mago",
  "WizardStudy": "Estudio de mago",
  "WizardEndTable": "Mesilla de mago",
  "WitchBroom": "Escoba de bruja",
  "Cauldron": "Caldero",
  "CurlyTree": "Árbol enroscado",
  "LeafyPlant": "Planta de pantano",
  "WizardChair": "Silla de mago",
  "WizardTable": "Mesa de mago",
  "WizardCushion": "Cojín de mago",
  "DarkWizardCushion": "Cojín de mago oscuro",
  "WizardTeaTable": "Mesita de té de mago",
  "SmallElixirShelf": "Estantería de elíxir pequeña",
  "ElixirShelf": "Estantería de elíxir",
  "SmallStackedElixirShelf": "Estantería de elíxir apilado pequeña",
  "StackedElixirShelf": "Estantería de elíxir apilado",
  "ElixirBundle": "Paquete de elíxires",
  "CoupleElixirs": "Dos elíxires",
  "ElixirTable": "Mesa de elíxir",
  "LongElixirTable": "Mesa larga de elíxir",
  "WizardLamp": "Lámpara de mago",
  "Runes": "« Runas »",
  "WizardTower": "« Torre del mago »",
  "PottedRedMushroom": "Seta moja en maceta",
  "WizardCatalogue": "Catálogo de mago",
  "VoidSwirls": "« Espirales de vacío »",
  "WizardBookshelf": "Estante de mago",
  "Glyph": "Glifo",
  "StoneFlooring": "Suelo de piedra",
  "RuneRug": "Alfombra rúnica",
  "SwirlRug": "Alfombra espiral",
  "StarryMoonRug": "Alfombra luna estrellada",
  "CrystalBall": "Bola de cristal",
  "AmethystCrystalBall": "Bola de cristal de amatista",
  "TopazCrystalBall": "Bola de cristal de topacio",
  "AquamarineCrystalBall": "Bola de cristal de aguamarina",
  "EmeraldCrystalBall": "Bola de cristal de esmeralda",
  "RubyCrystalBall": "Bola de cristal de rubí",
  "SmallBookStack": "Montón de libros pequeño",
  "BookStack": "Montón de libros",
  "LargeBookStack": "Montón de libros grande",
  "PurpleBook": "Libro morado",
  "BlueBook": "Libro azul",
  "YellowBook": "Libro amarillo",
  "RedBook": "Libro rojo",
  "GreenBook": "Libro verde",
  "BrownBook": "Libro marrón",
  "FallenPurpleBook": "Libro morado caído",
  "FallenBlueBook": "Libro azul caído",
  "FallenYellowBook": "Libro amarillo caído",
  "FallenRedBook": "Libro rojo caído",
  "FallenGreenBook": "Libro verde caído",
  "FallenBrownBook": "Libro marrón caído",
  "SmallBookPile": "Pila de libros pequeña",
  "BookPile": "Pila de libros",
  "LargeBookPile": "Pila de libros grande",
  "DecorativeWizardDoor": "Puerta de mago decorativa",
  "JunimoBed": "Cama junimo",
  "JunimoHut": "Cabaña junimo",
  "LargeJunimoHut": "Cabaña junimo grande",
  "SmallJunimoHut": "Cabaña junimo pequeña",
  "JunimoFireplace": "Chimenea junimo",
  "JunimoBookcase": "Librería junimo",
  "JunimoPot": "Maceta junimo",
  "JunimoBag": "Bolsa junimo",
  "JunimoBundle": "Paquete junimo",
  "JunimoStool": "Taburete junimo",
  "JunimoTable": "Mesa junimo",
  "JunimoChair": "Silla junimo",
  "SmallJunimoPot": "Maceta junimo pequeña",
  "JunimoFlower": "Flor junimo",
  "JunimoEndTable": "Mesilla junimo",
  "JunimoCatalogue": "Catálogo junimo",
  "JunimoTeaTable": "Mesita de té junimo",
  "JunimoDresser": "Cómoda junimo",
  "JunimoLamp": "Lámpara junimo",
  "JunimoPlant": "Planta junimo",
  "JunimoWallPlaque": "Placa de pared junimo",
  "JunimoPlaque": "Placa junimo",
  "JunimoCushion": "Cojín junimo",
  "DarkJunimoCushion": "Cojín junimo oscuro",
  "JunimoTree": "Árbol junimo",
  "JunimoCouch": "Sofá junimo",
  "GreenSleepingJunimo": "Junimo verde durmiente",
  "BlueSleepingJunimo": "Junimo azul durmiente",
  "RedSleepingJunimo": "Junimo rojo durmiente",
  "PurpleSleepingJunimo": "Junimo morado durmiente",
  "YellowSleepingJunimo": "Junimo amarillo durmiente",
  "OrangeSleepingJunimo": "Junimo naranja durmiente",
  "GraySleepingJunimo": "Junimo gris durmiente",
  "SquareJunimoRug": "Alfombra junimo cuadrada",
  "JunimoRug": "Alfombra junimo",
  "JunimoMat": "Alfombrilla junimo",
  "CircularJunimoRug": "Alfombra junimo circular",
  "SmallJunimoMat": "Alfombrilla junimo pequeña",
  "CommunityCenter": "« Centro cívico »",
  "LittleBuddies": "« Coleguitas »",
  "Stardrop": "« Fruta estelar »",
  "Hut": "« Cabaña »",
  "AbigailPortrait": "Retrato de Abigail",
  "EmilyPortrait": "Retrato de Emily",
  "HaleyPortrait": "Retrato de Haley",
  "LeahPortrait": "Retrato de Leah",
  "MaruPortrait": "Retrato de Maru",
  "PennyPortrait": "Retrato de Penny",
  "AlexPortrait": "Retrato de Alex",
  "ElliottPortrait": "Retrato de Elliott",
  "HarveyPortrait": "Retrato de Harvey",
  "SamPortrait": "Retrato de Sam",
  "SebastianPortrait": "Retrato de Sebastian",
  "ShanePortrait": "Retrato de Shane",
  "KrobusPortrait": "Retrato de Krobus",
  "JunimoStar": "Estrella junimo",
  "BulletinBoard": "Tablón de anuncios",
  "BrochureCabinet": "Expositor de folletos",
  "LeafyWallPanel": "Panel de pared arbolado",
  "LightLeafyWallPanel": "Panel de pared arbolado claro",
  "DarkLeafyWallPanel": "Panel de pared arbolado oscuro",
  "DecorativeJunimoDoor": "Puerta junimo decorativa",
  "RetroBed": "Cama retro",
  "RetroDresser": "Cómoda retro",
  "RetroBookcase": "Librería retro",
  "RetroFireplace": "Chimenea retro",
  "RetroCouch": "Sofá retro",
  "RetroCushion": "Cojín retro",
  "DarkRetroCushion": "Cojín retro oscuro",
  "RetroStool": "Taburete retro",
  "RetroFlower": "Flor retro",
  "RetroChair": "Silla retro",
  "RetroTable": "Mesa retro",
  "RetroPlant": "Planta retro",
  "RetroEndTable": "Mesilla retro",
  "RetroTeaTable": "Mesita de té retro",
  "RetroCatalogue": "Catálogo retro",
  "RetroCabinet": "Armario retro",
  "RetroRadio": "Radio retro",
  "RetroBanner": "Cartel retro",
  "Groovy": "« Guay »",
  "RetroLamp": "Lámpara retro",
  "RetroRug": "Alfombra retro",
  "RetroSquareRug": "Alfombra retro cuadrada",
  "RetroMat": "Alfombrilla retro",
  "LargeRetroRug": "Alfombra retro grande",
  "Abstract": "« Abstracto »",
  "Starship": "« Nave espacial »",
  "Binary": "« Binario »",
  "Checkers": "« Damas »",
  "UFO": "« OVNI »",
  "DecorativeRetroDoor": "Puerta retro decorativa",
  "DecorativeDoor1": "Puerta decorativa",
  "DecorativeDoor2": "Puerta decorativa",
  "DecorativeDoor3": "Puerta decorativa",
  "DecorativeDoor4": "Puerta decorativa",
  "DecorativeDoor5": "Puerta decorativa",
  "DecorativeDoor6": "Puerta decorativa",
  "WallClock": "Reloj de pared",
  "DecorativeHatch": "Trampilla decorativa",
  "DecorativeOakLadder": "Escalera de roble decorativa",
  "DecorativeWalnutLadder": "Escalera de nogal decorativa",
  "UprightPiano": "Piano vertical",
  "CoatStand": "Perchero",
  "BirdHouse": "Pajarera",
  "DecorativeShovel": "Pala decorativa",
  "WallSword": "Espada de pared",
  "DecorativeSword": "Espada decorativa",
  "WineTable": "Mesa de vino",
  "SpiritsTable": "Mesa de licor",
  "TallHousePlant": "Planta de interior alta",
  "CornPlant": "Planta de maíz",
  "BlueCushion": "Cojín azul",
  "YellowCushion": "Cojín amarillo",
  "GreenCushion": "Cojín verde",
  "RedCushion": "Cojín rojo",
  "BrownCushion": "Cojín marrón",
  "BlackCushion": "Cojín negro",
  "FoodPetBowl": "Comedero",
  "WaterPetBowl": "Bebedero",
  "OakLampEndTable": "Mesilla con lámpara de roble",
  "WalnutLampEndTable": "Mesilla con lámpara de nogal",
  "BirchLampEndTable": "Mesilla con lámpara de abedul",
  "MahoganyLampEndTable": "Mesilla con lámpara de caoba",
  "TriangleWindow": "Ventana triangular",
  "Clothesline": "Tendedero",
  "TrashCatalogue": "Catálogo basura",
  "ElegantVase": "Jarrón elegante",
  "CatTree": "Árbol rascador para gatos",
  "DarkCatTree": "Árbol rascador para gatos oscuro",
  "LightSwitch": "Interruptor",
  "Outlet": "Enchufe",
  "Doghouse": "Caseta para perro",
  "DarkDoghouse": "Caseta para perro oscura",
  "BountifulDiningTable": "Mesa de comedor abundante",
  "PlasticLawnEndTable": "Mesilla para patio de plástico",
  "PlasticLawnChair": "Silla para patio de plástico",
  "BrokenTelevision": "Televisión rota",
  "SixPackRings": "Anillos de plástico para latas",
  "GreenBottle": "Botella verde",
  "PlasticBag": "Bolsa de plástico",
  "AluminumCan": "Lata de aluminio",
  "BlueBottle": "Botella azul",
  "BuriedTire": "Neumático enterrado",
  "Tire": "Neumático",
  "Wrapper": "Envoltorio",
  "SpilledBeverage": "Bebida derramada",
  "MessyShirt": "Camisa arrugada",
  "MessyShorts": "Pantalón corto arrugado",
  "MoldyCouch": "Sofá mohoso",
  "FancyHousePlant": "Planta de interior lujosa",
  "PigPainting": "Cuadro de cerdo",
  "MidnightBed": "Cama de playa de medianoche",
  "MidnightDoubleBed": "Cama doble de playa de medianoche"
}