{
  "Abigail": "アビゲイル",
  "Alex": "アレックス",
  "Bear": "クマ",
  "Birdie": "バーディー",
  "Bouncer": "用心棒",
  "Caroline": "キャロライン",
  "Clint": "クリント",
  "Demetrius": "ディメトリウス",
  "Dwarf": "ドワーフ",
  "Elliott": "エリオット",
  "Emily": "エミリー",
  "Evelyn": "エブリン",
  "George": "ジョージ",
  "Gil": "ギル",
  "Governor": "市長",
  "Grandpa": "おじいさん",
  "Gunther": "ギュンター",
  "Gus": "ガス",
  "Haley": "ヘイリー",
  "Harvey": "ハーヴィー",
  "Henchman": "部下",
  "Jas": "ジャス",
  "Jodi": "ジョディ",
  "Kent": "ケント",
  "Krobus": "クロバス",
  "Leah": "リア",
  "Leo": "レオ",
  "Lewis": "ルイス",
  "Linus": "ライナス",
  "Marlon": "マーロン",
  "Marnie": "マーニー",
  "Maru": "マル",
  "MisterQi": "ミスターQi",
  "Morris": "モーリス",
  "OldMariner": "年老いた水夫",
  "Pam": "パム",
  "Penny": "ペニー",
  "Pierre": "ピエール",
  "ProfessorSnail": "スネイル教授",
  "Robin": "ロビン",
  "Sam": "サム",
  "Sandy": "サンディ",
  "Sebastian": "セバスチャン",
  "Shane": "シェーン",
  "Vincent": "ヴィンセント",
  "Welwick": "ウェルウィック",
  "Willy": "ウィリー",
  "Wizard": "魔術師",
  "Fizz": "フィズ"
}