{"name":"Krobus","avatar":"https://stardewcommunitywiki.com/mediawiki/images/7/71/Krobus.png","birthday":"Winter 1","bestGifts":["Diamond","Iridium Bar","Pumpkin","Void Egg","Void Mayonnaise","Wild Horseradish"],"gifts":{"love":["Universal Loves","Diamond","Iridium Bar","Pumpkin","Void Egg","Void Mayonnaise","Wild Horseradish"],"like":["Universal Likes (except Life Elixir and","Cooking other than Seafoam Pudding)","Gold Bar","Quartz"],"dislike":["Universal Dislikes (except Gold Bar, Iridium Bar, & Void Egg)","Cooking (except Bread, Fried Egg, Seafoam Pudding, & Strange Bun)","Chanterelle","Common Mushroom","Daffodil","Dandelion","Ginger","Hazelnut","Holly","Leek","Life Elixir","Magma Cap","Morel","Purple Mushroom","Salmonberry","Snow Yam","Winter Root"],"neutral":["Universal Neutrals","Eggs (except Void Egg)*","Fruit (except Fruit Tree Fruit & Salmonberry)","Milk"],"hate":["Universal Hates (except Void Mayonnaise)"]},"canMarry":false,"wiki":"https://stardewcommunitywiki.com/Krobus"}